bronzebeard/__init__.py
bronzebeard/asm.py
bronzebeard/dfu.py
bronzebeard/definitions/ESP8266.asm
bronzebeard/definitions/FE310-G002.asm
bronzebeard/definitions/GD32VF103.asm
bronzebeard/definitions/ST7735S.asm
bronzebeard/libs/libusb-1.0.dll
bronzebeard-0.2.2.dist-info/LICENSE
bronzebeard-0.2.2.dist-info/METADATA
bronzebeard-0.2.2.dist-info/WHEEL
bronzebeard-0.2.2.dist-info/entry_points.txt
bronzebeard-0.2.2.dist-info/top_level.txt
bronzebeard-0.2.2.dist-info/RECORD
