Metadata-Version: 2.1
Name: bronzebeard
Version: 0.2.2
Summary: Minimal ecosystem for bare-metal RISC-V development
Home-page: https://github.com/theandrew168/bronzebeard
Author: Andrew Dailey
Author-email: andrew@shallowbrooksoftware.com
Project-URL: Documentation, https://bronzebeard.readthedocs.io
Project-URL: Source Code, https://github.com/theandrew168/bronzebeard
Project-URL: Issue Tracker, https://github.com/theandrew168/bronzebeard/issues
Classifier: Development Status :: 4 - Beta
Classifier: Environment :: Console
Classifier: Intended Audience :: Developers
Classifier: License :: OSI Approved :: MIT License
Classifier: Operating System :: OS Independent
Classifier: Programming Language :: Assembly
Classifier: Programming Language :: Python :: 3
Classifier: Topic :: Software Development
Classifier: Topic :: Software Development :: Assemblers
Classifier: Topic :: Software Development :: Embedded Systems
Requires-Python: >=3.6
License-File: LICENSE
Requires-Dist: intelhex
Requires-Dist: pyserial
Requires-Dist: pyusb
